examples/VariantTaskExample.py
examples/__init__.py
examples/example_classification.py
examples/example_task_runner.py
examples/language_example.py
taskdl/TaskWrapper.py
taskdl/__init__.py
taskdl/tf_task.py
taskdl-0.1.5.dist-info/LICENSE
taskdl-0.1.5.dist-info/METADATA
taskdl-0.1.5.dist-info/WHEEL
taskdl-0.1.5.dist-info/top_level.txt
taskdl-0.1.5.dist-info/RECORD
